ndev_workflows/__init__.py
ndev_workflows/_batch.py
ndev_workflows/_io.py
ndev_workflows/_io_legacy.py
ndev_workflows/_manager.py
ndev_workflows/_spec.py
ndev_workflows/_undo_redo.py
ndev_workflows/_version.py
ndev_workflows/_workflow.py
ndev_workflows/napari.yaml
ndev_workflows/widgets/__init__.py
ndev_workflows/widgets/_workflow_container.py
ndev_workflows-0.0.1.dist-info/licenses/LICENSE
ndev_workflows-0.0.1.dist-info/METADATA
ndev_workflows-0.0.1.dist-info/WHEEL
ndev_workflows-0.0.1.dist-info/entry_points.txt
ndev_workflows-0.0.1.dist-info/top_level.txt
ndev_workflows-0.0.1.dist-info/RECORD
