Metadata-Version: 2.4
Name: ndev-workflows
Version: 0.0.1
Summary: reproducible processing workflows with napari
Author: Tim Monko
Author-email: timmonko@gmail.com
License-Expression: BSD-3-Clause
Project-URL: Bug Tracker, https://github.com/ndev-kit/ndev-workflows/issues
Project-URL: Documentation, https://github.com/ndev-kit/ndev-workflows#README.md
Project-URL: Source Code, https://github.com/ndev-kit/ndev-workflows
Project-URL: User Support, https://github.com/ndev-kit/ndev-workflows/issues
Classifier: Development Status :: 2 - Pre-Alpha
Classifier: Framework :: napari
Classifier: Intended Audience :: Developers
Classifier: Operating System :: OS Independent
Classifier: Programming Language :: Python
Classifier: Programming Language :: Python :: 3
Classifier: Programming Language :: Python :: 3 :: Only
Classifier: Programming Language :: Python :: 3.11
Classifier: Programming Language :: Python :: 3.12
Classifier: Programming Language :: Python :: 3.13
Classifier: Topic :: Scientific/Engineering :: Image Processing
Requires-Python: >=3.11
License-File: LICENSE
Requires-Dist: napari
Requires-Dist: nbatch>=0.0.4
Requires-Dist: ndevio>=0.6.0
Requires-Dist: magicgui
Requires-Dist: magic-class
Requires-Dist: numpy
Requires-Dist: dask
Requires-Dist: pyyaml
Provides-Extra: all
Requires-Dist: napari[all]; extra == "all"
Dynamic: license-file
